pylibvw.cpython-38-x86_64-linux-gnu.so
vowpalwabbit-9.10.0.dist-info/RECORD
vowpalwabbit-9.10.0.dist-info/top_level.txt
vowpalwabbit-9.10.0.dist-info/LICENSE
vowpalwabbit-9.10.0.dist-info/WHEEL
vowpalwabbit-9.10.0.dist-info/METADATA
vowpalwabbit-9.10.0.dist-info/AUTHORS
vowpalwabbit/pyvw.py
vowpalwabbit/version.py
vowpalwabbit/sklearn_vw.py
vowpalwabbit/__init__.py
vowpalwabbit/conda_install.sh
vowpalwabbit/dftovw.py
vowpalwabbit/sklearn.py
vowpalwabbit/__main__.py
