Metadata-Version: 2.1
Name: vowpalwabbit
Version: 9.10.0
Summary: Vowpal Wabbit Python package
Home-page: https://github.com/VowpalWabbit/vowpal_wabbit
Author: Scott Graham
Author-email: scott.d.graham@gmail.com
License: BSD 3-Clause License
Keywords: fast machine learning online classification regression
Platform: any
Classifier: Development Status :: 4 - Beta
Classifier: Intended Audience :: Science/Research
Classifier: Topic :: Scientific/Engineering
Classifier: Topic :: Scientific/Engineering :: Information Analysis
Classifier: License :: OSI Approved :: BSD License
Classifier: Programming Language :: Python :: 3
Requires-Python: >=3.6
